{
  "match_count": 10,
  "matches": [
    {
      "name": "Earl Luna",
      "phone": "532.603.3230x9821",
      "match_score": 49.52,
      "details": {
        "skills": 84.35,
        "experience+company": 30.0,
        "role_match": 50.0,
        "total_experience_years": 1.0,
        "education": 50.0,
        "location": 30.0,
        "language_bonus": 2.5
      }
    },
    {
      "name": "Jasmine Mosley",
      "phone": "0011850163159x9965",
      "match_score": 45.25,
      "details": {
        "skills": 30.71,
        "experience+company": 30.0,
        "role_match": 50.0,
        "total_experience_years": 1.0,
        "education": 100.0,
        "location": 100.0,
        "language_bonus": 2.5
      }
    },
    {
      "name": "Samantha Sanders",
      "phone": "1715454443x2830",
      "match_score": 38.3,
      "details": {
        "skills": 30.87,
        "experience+company": 30.0,
        "role_match": 50.0,
        "total_experience_years": 1.0,
        "education": 100.0,
        "location": 30.0,
        "language_bonus": 2.5
      }
    },
    {
      "name": "Brent Rodgers",
      "phone": "0010494519832x7315",
      "match_score": 38.26,
      "details": {
        "skills": 30.75,
        "experience+company": 30.0,
        "role_match": 50.0,
        "total_experience_years": 1.0,
        "education": 100.0,
        "location": 30.0,
        "language_bonus": 2.5
      }
    },
    {
      "name": "Kelly Hammond",
      "phone": "0018922680182x42253",
      "match_score": 35.32,
      "details": {
        "skills": 30.9,
        "experience+company": 30.0,
        "role_match": 50.0,
        "total_experience_years": 1.0,
        "education": 100.0,
        "location": 0.0,
        "language_bonus": 2.5
      }
    },
    {
      "name": "Zachary Sanford",
      "phone": "1355215704x33154",
      "match_score": 34.33,
      "details": {
        "skills": 19.52,
        "experience+company": 30.0,
        "role_match": 50.0,
        "total_experience_years": 1.0,
        "education": 100.0,
        "location": 30.0,
        "language_bonus": 2.5
      }
    },
    {
      "name": "Patricia Baker",
      "phone": "364.710.2767x7359",
      "match_score": 33.34,
      "details": {
        "skills": 30.98,
        "experience+company": 30.0,
        "role_match": 50.0,
        "total_experience_years": 1.0,
        "education": 50.0,
        "location": 80.0,
        "language_bonus": 0.0
      }
    },
    {
      "name": "Bobby Cook",
      "phone": "0012712966667x60083",
      "match_score": 32.72,
      "details": {
        "skills": 30.64,
        "experience+company": 30.0,
        "role_match": 50.0,
        "total_experience_years": 1.0,
        "education": 100.0,
        "location": 0.0,
        "language_bonus": 0.0
      }
    },
    {
      "name": "Robert Williams",
      "phone": "875.099.7700",
      "match_score": 31.87,
      "details": {
        "skills": 19.63,
        "experience+company": 30.0,
        "role_match": 50.0,
        "total_experience_years": 1.0,
        "education": 100.0,
        "location": 30.0,
        "language_bonus": 0.0
      }
    },
    {
      "name": "Tammy Boone",
      "phone": "0018373540331x7393",
      "match_score": 31.33,
      "details": {
        "skills": 19.52,
        "experience+company": 30.0,
        "role_match": 50.0,
        "total_experience_years": 1.0,
        "education": 100.0,
        "location": 0.0,
        "language_bonus": 2.5
      }
    }
  ]
}